solTg/ReportBuilder.py
solTg/RunAll.py
solTg/SolParser.py
solTg/SolidityTestGen.py
solTg/TestWrapper.py
solTg/Utils.py
solTg/__init__.py
solTg_plus-0.2.2.data/data/deps/solc
solTg_plus-0.2.2.data/data/deps/tgnonlin
solTg_plus-0.2.2.dist-info/LICENSE.txt
solTg_plus-0.2.2.dist-info/METADATA
solTg_plus-0.2.2.dist-info/WHEEL
solTg_plus-0.2.2.dist-info/entry_points.txt
solTg_plus-0.2.2.dist-info/top_level.txt
solTg_plus-0.2.2.dist-info/RECORD
