Metadata-Version: 2.2
Name: solTg-plus
Version: 0.2.2
Summary: Test generation for Solidity in Foundry format (https://github.com/foundry-rs/foundry).
Home-page: https://github.com/zuru-zuru/soltgbackend
Author: Konstantin Britikov
Author-email: BritikovKI@Gmail.com
License: GPL-3.0-only
Requires-Python: >3.5.2
License-File: LICENSE.txt
Requires-Dist: eth-hash==0.5.2
Requires-Dist: eth-typing==3.5.2
Requires-Dist: eth-utils==2.3.1
Requires-Dist: exceptiongroup==1.1.1
Requires-Dist: matplotlib==3.7.1
Requires-Dist: numpy<2
Requires-Dist: networkx==3.1
Requires-Dist: packaging==23.0
Requires-Dist: pycryptodome==3.19.1
Requires-Dist: pyparsing==3.0.9
Requires-Dist: requests==2.31.0
Requires-Dist: selenium==4.10.0
Requires-Dist: sniffio==1.3.0
Requires-Dist: sortedcontainers==2.4.0
Requires-Dist: zipp==3.15.0
Requires-Dist: xlsxwriter==3.1.9
Requires-Dist: setuptools
Dynamic: author
Dynamic: author-email
Dynamic: description
Dynamic: description-content-type
Dynamic: home-page
Dynamic: license
Dynamic: requires-dist
Dynamic: requires-python
Dynamic: summary
